tasker/__init__.py
tasker/__main__.py
tasker/cli.py
tasker/database.py
tasker/models.py
python_tasker-0.1.0.dist-info/METADATA
python_tasker-0.1.0.dist-info/WHEEL
python_tasker-0.1.0.dist-info/entry_points.txt
python_tasker-0.1.0.dist-info/top_level.txt
python_tasker-0.1.0.dist-info/RECORD
