Metadata-Version: 2.4
Name: python-tasker
Version: 0.1.0
Summary: A simple CLI todo list using SQLite and Typer
Author: Adrian Tudev
License: MIT
Requires-Dist: typer
